{
    "miniprogramRoot": "dist/",
    "projectname": "projrct-taro-react",
    "description": "taro of react",
    "appid": "wx61e04e3c2ce6d21e",
    "setting": {
        "urlCheck": true,
        "scopeDataCheck": false,
        "coverView": true,
        "es6": false,
        "postcss": true,
        "compileHotReLoad": false,
        "lazyloadPlaceholderEnable": false,
        "preloadBackgroundData": false,
        "minified": true,
        "autoAudits": false,
        "newFeature": false,
        "uglifyFileName": false,
        "uploadWithSourceMap": true,
        "useIsolateContext": false,
        "nodeModules": false,
        "enhance": true,
        "useMultiFrameRuntime": true,
        "useApiHook": true,
        "useApiHostProcess": true,
        "showShadowRootInWxmlPanel": true,
        "packNpmManually": false,
        "packNpmRelationList": [],
        "minifyWXSS": true,
        "disableUseStrict": false,
        "minifyWXML": true,
        "babelSetting": {
            "ignore": [],
            "disablePlugins": [],
            "outputPath": ""
        }
    },
    "compileType": "miniprogram",
    "condition": {},
    "libVersion": "2.29.0",
    "srcMiniprogramRoot": "dist/",
    "packOptions": {
        "ignore": [],
        "include": []
    },
    "editorSetting": {
        "tabIndent": "insertSpaces",
        "tabSize": 4
    }
}